README.md
setup.py
number_to_chinese/__init__.py
number_to_chinese/cctan.py
number_to_chinese.egg-info/PKG-INFO
number_to_chinese.egg-info/SOURCES.txt
number_to_chinese.egg-info/dependency_links.txt
number_to_chinese.egg-info/top_level.txt
number_to_chinese.egg-info/zip-safe