Metadata-Version: 1.1
Name: number_to_chinese
Version: 1.0.0
Summary: this is a Capital Chinese to Arabic numerals package.
Home-page: http://blog.useasp.net/
Author: Wangyiyao
Author-email: 1738698834@qq.com
License: MIT
Keywords: chinese transform char number python package
Platform: UNKNOWN
Classifier: License :: OSI Approved :: MIT License
Classifier: Programming Language :: Python
Classifier: Intended Audience :: Developers
Classifier: Operating System :: Microsoft :: Windows
Classifier: Operating System :: MacOS
Classifier: Operating System :: Unix
Classifier: Programming Language :: Python :: 2.7
